{
  "numSong": 63,
  "api": [
    {
      "title": "Overtaken (One Piece OST)",
      "singer": "Shirō Hamaguchi",
      "url":
          "https://github.com/acrosshorizon/palpitate/blob/main/Piano320Kpbs/Overtaken%20-%20One%20Piece%20OST.mp3?raw=true",
      "coverUrl":
          "https://i.pinimg.com/originals/35/9d/9c/359d9c5d36d35f34af477c54c7e2abe1.gif",
      "info":
          "https://www.youtube.com/watch?v=ol9gQ-WtXnk",
      "cover": "(Cover by Thomas R. Piano)"
    },
    {
      "title":"Summer of Goodbye (From Up on Poppy Hill)",
      "singer":"Aoi Teshima",
      "url":"https://github.com/acrosshorizon/palpitate_v2/blob/main/piano/From%20up%20on%20Poppy%20Hill%20-%20Summer%20of%20Goodbye%20-%20Piano%20version.mp3?raw=true",
      "coverUrl":"https://i.pinimg.com/736x/ff/b6/91/ffb691c73d3d24a8857ae7ecc454eb17.jpg",
      "info":"https://www.youtube.com/watch?v=WZFWpY2tAcE&list=PLTpeyQJ-cKQfkJ12WuqDbbYPYJkdv7Usm&index=239",
      "cover":"Flo"
   },
    {
      "title":"Konayuki (1 Litre of tear)",
      "singer":"Remioromen",
      "url":"https://github.com/acrosshorizon/palpitate_v2/blob/main/piano/Konayuki%20-%20(Ray%20Krislianggi).mp3?raw=true",
      "coverUrl":"https://i.pinimg.com/564x/93/00/e4/9300e49ab2e6b947b937f335777322d0.jpg",
      "info":"https://www.youtube.com/watch?v=9Z16Ez-HSEo&list=PLTpeyQJ-cKQfkJ12WuqDbbYPYJkdv7Usm&index=214",
      "cover":"Ray Krislianggi"
   },
   {
      "title":"Konayuki (1 Litre of tear)",
      "singer":"Remioromen",
      "url":"https://github.com/acrosshorizon/palpitate_v2/blob/main/piano/1%20Litre%20of%20Tears%20-%20Konayuki%20(%E7%B2%89%E9%9B%AA)%20~Piano%20Version~.mp3?raw=true",
      "coverUrl":"https://i.pinimg.com/originals/9c/ed/42/9ced428955c650aa35a7558aca68b184.gif",
      "info":"https://www.youtube.com/watch?v=2RALgHDi2_g&list=PLTpeyQJ-cKQfkJ12WuqDbbYPYJkdv7Usm&index=213",
      "cover":"The Piano Noob"
   },
   {
      "title":"Song from a Secret Garden (Secret Garden)",
      "singer":"Secret Garden",
      "url":"https://github.com/acrosshorizon/palpitate_v2/blob/main/piano/Song%20from%20a%20Secret%20Garden%F0%9F%8C%BF%EC%8B%A0%EB%B9%84%EB%A1%9C%EC%9A%B4%20%EA%B0%90%EC%84%B1%EC%9D%98%20%EC%B2%BC%EB%A1%9C%EC%97%B0%EC%A3%BC%F0%9F%96%A4.mp3?raw=true",
      "coverUrl":"https://i.pinimg.com/564x/b0/0b/49/b00b49f9d2c0c17322588cef3d2a6117.jpg",
      "info":"https://www.youtube.com/watch?v=MfwJ4X7lx4k&list=PLTpeyQJ-cKQfkJ12WuqDbbYPYJkdv7Usm&index=207",
      "cover":"CelloDeck 첼로댁"
   },
    {
      "title":"Your Lie in April Medley",
      "singer":"AmaLee",
      "url":"https://github.com/acrosshorizon/palpitate_v2/blob/main/piano/Your%20Lie%20in%20April%20Medley%20-%20(albie).mp3?raw=true",
      "coverUrl":"https://i.pinimg.com/564x/8e/2d/27/8e2d27abd5285e213539fd9b7f1b2779.jpg",
      "info":"https://www.youtube.com/watch?v=j1Xf7AxO2a0&list=PLTpeyQJ-cKQfkJ12WuqDbbYPYJkdv7Usm&index=243",
      "cover":"albie"
   },
   {
      "title":"Orange (Your lie in April)",
      "singer":"7!",
      "url":"https://github.com/acrosshorizon/palpitate_v2/blob/main/piano/Your%20lie%20in%20April%20-%20(Fonzi%20M%20-%20Melodies%20on%20Piano).mp3?raw=true",
      "coverUrl":"https://i.pinimg.com/564x/8a/22/bd/8a22bd5d519fb91f2dd6efc7c2f3122c.jpg",
      "info":"https://www.youtube.com/watch?v=Z_po9Vywn0s&list=PLTpeyQJ-cKQfkJ12WuqDbbYPYJkdv7Usm&index=242",
      "cover":"Fonzi M - Melodies on Piano"
   },
    {
      "title": "Guren no Yumiya (Attack on Titan)",
      "singer": "Linked Horizon",
      "url":
          "https://github.com/acrosshorizon/palpitate/blob/main/Piano320Kpbs/Attack%20on%20Titan%20-%20%20Guren%20no%20Yumiya%20-%20(Patrik%20Pietschmann).mp3?raw=true",
      "coverUrl":
          "https://media.tenor.com/YBSVvmO8XK8AAAAM/attack-on-titan-hungry.gif",
      "info":
          "https://www.youtube.com/watch?v=MIUQGbA8B4k&list=PLTpeyQJ-cKQfkJ12WuqDbbYPYJkdv7Usm&index=80",
      "cover": "(Cover by Patrik Pietschmann)"
    },
    {
      "title":"Mezase Pokémon Master",
      "singer":"Rica Matsumoto",
      "url":"https://github.com/acrosshorizon/palpitate_v2/blob/main/musicbox/Mezase%20Pok%C3%A9mon%20Master%20-%20Rica%20Matsumoto%20%5BMusic%20Box%5D%20(Anime%20%23Pok%C3%A9mon%23%20OP).mp3?raw=true",
      "coverUrl":"https://avatarfiles.alphacoders.com/989/98932.gif",
      "info":"https://www.youtube.com/watch?v=wcqxQ49pOvY&list=PLTpeyQJ-cKQfkJ12WuqDbbYPYJkdv7Usm&index=171",
      "cover":"R3 Music Box"
    },
    {
      "title": "Attack on Titan (Main Theme)",
      "singer": "Unknown",
      "url":
          "https://github.com/acrosshorizon/palpitate/blob/main/Piano320Kpbs/Attack%20on%20Titan%20(Main%20Theme)%20-%20(Animenz%20Piano%20Sheets).mp3?raw=true",
      "coverUrl":
          "https://giffiles.alphacoders.com/114/114540.gif",
      "info":
          "https://www.youtube.com/watch?v=69lx6TvQTFg&list=PLTpeyQJ-cKQfkJ12WuqDbbYPYJkdv7Usm&index=79",
      "cover": "(Cover by Animenz Piano Sheets)"
    },
    {
      "title": "Doraemon No Uta",
      "singer": "Yamano Satoko ",
      "url":
          "https://github.com/acrosshorizon/palpitate/blob/main/Piano320Kpbs/Doraemon%20No%20Uta%20-%20(Upwan%20Jindal).mp3?raw=true",
      "coverUrl":
          "https://i.pinimg.com/originals/79/90/74/799074c7a9eaf9cfd54e3c47bb1ea501.gif",
      "info":
          "https://www.youtube.com/watch?v=dX9JsEdLWCs&list=PLTpeyQJ-cKQfkJ12WuqDbbYPYJkdv7Usm&index=78",
      "cover": "(Cover by Upwan Jindal)"
    },
    {
      "title": "Overtaken (One Piece OST)",
      "singer": "Unknown",
      "url":
          "https://github.com/acrosshorizon/palpitate/blob/main/Piano320Kpbs/Overtaken%20Piano%20Cover%20-%20One%20Piece%20OST%20-%20(Thomas%20R.%20Piano).mp3?raw=true",
      "coverUrl":
          "https://i.pinimg.com/originals/75/67/34/756734cc591e3b3ef966d9eadffc3b22.gif",
      "info":
          "https://www.youtube.com/watch?v=ol9gQ-WtXnk&list=PLTpeyQJ-cKQfkJ12WuqDbbYPYJkdv7Usm&index=82",
      "cover": "(Cover by Thomas R. Piano)"
    },
    {
      "title": "We Are! (One Piece OP1)",
      "singer": "Hiroshi Kitadani",
      "url":
          "https://github.com/acrosshorizon/palpitate/blob/main/Piano320Kpbs/We%20Are!%20-%20One%20Piece%20OP1%20%5BPiano%5D%20-%20(Animenz%20Piano%20Sheets).mp3?raw=true",
      "coverUrl":
          "https://media.tenor.com/A32q04Ml-DwAAAAC/tony-tony-tony-chopper.gif",
      "info":
          "https://www.youtube.com/watch?v=_iHe7-RhP1I&list=PLTpeyQJ-cKQfkJ12WuqDbbYPYJkdv7Usm&index=81",
      "cover": "(Cover by Animenz Piano Sheets)"
    },
    {
      "title": "Orange (Your Lie in April OST)",
      "singer": "7!!",
      "url":
          "https://github.com/acrosshorizon/palpitate/blob/main/Piano320Kpbs/Your%20Lie%20in%20April%E3%80%8COrange%20%20%E3%82%AA%E3%83%AC%E3%83%B3%E3%82%B8%20-%207!!%E3%80%8DRu's%20Piano%20-%20(Ru's%20Piano%20Ru%E5%91%B3%E6%98%A5%E6%8D%B2).mp3?raw=true",
      "coverUrl":
          "https://giffiles.alphacoders.com/139/13987.gif",
      "info":
          "https://www.youtube.com/watch?v=GEYepRwYKHw&list=PLTpeyQJ-cKQfkJ12WuqDbbYPYJkdv7Usm&index=84",
      "cover": "(Cover by Ru's Piano Ru味春捲)"
    },
    {
      "title": "Always With Me (Spirited Away OST)",
      "singer": "Youmi Kimura",
      "url":
          "https://github.com/acrosshorizon/palpitate/blob/main/Piano320Kpbs/Always%20With%20Me%20-%20Spirited%20Away%20(Piano)%20-%20(Ghibli%20Music).mp3?raw=true",
      "coverUrl":
          "https://thumbs.gfycat.com/CapitalIdealisticImperialeagle-size_restricted.gif",
      "info":
          "https://www.youtube.com/watch?v=ESJ7TQvFFrA&list=PLTpeyQJ-cKQfkJ12WuqDbbYPYJkdv7Usm&index=70",
      "cover": "(Cover by Ghibli Music)"
    },
    {
      "title": "Blue Bird (Naruto Shippuuden OP3)",
      "singer": "Ikimonogakari",
      "url":
          "https://github.com/acrosshorizon/palpitate/blob/main/Piano320Kpbs/Blue%20Bird%20-%20Naruto%20Shippuuden%20OP3%20-%20(Animenz%20Piano%20Sheets).mp3?raw=true",
      "coverUrl":
          "https://thumbs.gfycat.com/BewitchedUnsungGrayfox-size_restricted.gif",
      "info":
          "https://www.youtube.com/watch?v=FTrJ-J_lsr0&list=PLTpeyQJ-cKQfkJ12WuqDbbYPYJkdv7Usm&index=73",
      "cover": "(Cover by Animenz Piano Sheets)"
    },
    {
      "title": "Sadness and Sorrow (Naruto)",
      "singer": "Unknown",
      "url":
          "https://github.com/acrosshorizon/palpitate/blob/main/Piano320Kpbs/Naruto%20-%20Sadness%20and%20Sorrow%20Piano%20-%20(Patrik%20Pietschmann).mp3?raw=true",
      "coverUrl":
          "https://i.pinimg.com/originals/78/79/0f/78790fbb0df6995a5c8cf12878002d17.gif",
      "info":
          "https://www.youtube.com/watch?v=Kk60F8a7-Jw&list=PLTpeyQJ-cKQfkJ12WuqDbbYPYJkdv7Usm&index=74",
      "cover": "(Cover by Patrik Pietschmann)"
    },
    {
      "title": "One Summer's Day",
      "singer": "Joe Hisaishi",
      "url":
          "https://github.com/acrosshorizon/palpitate/blob/main/Piano320Kpbs/One%20Summer's%20Day%20-%20Joe%20Hisaishi%20-%20(Joe%20Hisaishi%20Official).mp3?raw=true",
      "coverUrl":
          "https://i.pinimg.com/564x/e2/ca/ca/e2caca6cd1086453264f2f04d2252a10.jpg",
      "info":
          "https://www.youtube.com/watch?v=TK1Ij_-mank&list=PLTpeyQJ-cKQfkJ12WuqDbbYPYJkdv7Usm&index=69",
      "cover": "(Cover by Joe Hisaishi Official)"
    },
    {
      "title": "Genshin Impact - Soar In the Wind (Kamisato Ayaka Tsubaki in Thawing Snow OST)",
      "singer": "",
      "url":
          "https://github.com/acrosshorizon/palpitate/blob/main/Piano320Kpbs/Soar%20In%20the%20Wind%20Kamisato%20Ayaka%20Tsubaki%20in%20Thawing%20Snow%20(Genshin%20Impact)%20Epic%20Piano%20-%20(ChaconneScott_ACG%20on%20Piano).mp3?raw=true",
      "coverUrl":
          "https://i.pinimg.com/originals/20/17/d8/2017d847fb9cb4115f1fdf4460d76b40.gif",
      "info":
          "https://www.youtube.com/watch?v=57tGgRIaqHw&list=PLTpeyQJ-cKQfkJ12WuqDbbYPYJkdv7Usm&index=72",
      "cover": "(Cover by ChaconneScott_ACG on Piano)"
    },
    {
      "title": "Tada Koe Hitotsu",
      "singer": "Rokudenashi",
      "url":
          "https://github.com/acrosshorizon/palpitate/blob/main/Piano320Kpbs/Tada%20Koe%20Hitotsu%20-%20Rokudenashi%20-%20(%E3%81%B0%E3%82%93%E3%81%91%E3%82%93Banken).mp3?raw=true",
      "coverUrl":
          "https://i1.sndcdn.com/artworks-HfRppQ0mVx8wEXxS-W0Pwxw-t500x500.jpg",
      "info":
          "https://www.youtube.com/watch?v=bZA9fPmFok0&list=PLTpeyQJ-cKQfkJ12WuqDbbYPYJkdv7Usm&index=68",
      "cover": "(Cover by ばんけんBanken)"
    },
    {
      "title": "Uchiage Hanabi",
      "singer": "DAOKO ft Kenshi Yonezu",
      "url":
          "https://github.com/acrosshorizon/palpitate/blob/main/Piano320Kpbs/Uchiage%20Hanabi%20%E6%89%93%E4%B8%8A%E8%8A%B1%E7%81%AB%20DAOKO%20%C3%97%20Kenshi%20Yonezu%20-%20(Ru's%20Piano%20Ru%E5%91%B3%E6%98%A5%E6%8D%B2).mp3?raw=true",
      "coverUrl":
          "https://i1.sndcdn.com/artworks-000358996056-il4s1i-t500x500.jpg",
      "info":
          "https://www.youtube.com/watch?v=bZUS4uW9FdQ&list=PLTpeyQJ-cKQfkJ12WuqDbbYPYJkdv7Usm&index=71",
      "cover": "(Cover by Ru's Piano Ru味春捲)"
    },
    {
      "title": "Doraemon no Uta",
      "singer": "Yamano Satoko",
      "url":
          "https://github.com/acrosshorizon/palpitate/blob/main/Guitar320Kpbs/Doraemon%20no%20Uta%20-%20(Jakarudi).mp3?raw=true",
      "coverUrl":
          "https://resizing.flixster.com/n6i_ggdcS-E_qTleKXXlu7-gQuc=/300x300/v2/https://flxt.tmsimg.com/assets/p12434794_k_v13_aa.jpg",
      "info":
          "https://www.youtube.com/watch?v=Z26lVIkH4KQ&list=PLTpeyQJ-cKQfkJ12WuqDbbYPYJkdv7Usm&index=77",
      "cover": "(Cover by Jakarudi)"
    },  
    {
      "title": "Sadness and Sorrow (Naruto OST)",
      "singer": "Taylor Davis",
      "url":
          "https://github.com/acrosshorizon/palpitate/blob/main/Piano320Kpbs/Naruto%20-%20Sadness%20and%20Sorrow%20(Piano%20Version)%20(320kbps).mp3?raw=true",
      "coverUrl":
          "https://i.pinimg.com/originals/72/ef/b6/72efb6d6ec916c03bc30c9d113c16ca9.gif",
      "info":
          "https://www.youtube.com/watch?v=Kk60F8a7-Jw",
      "cover": "(Cover by Patrik Pietschmann)"
    },
    {
      "title": "We Are! (One Piece OST)",
      "singer": "Hiroshi Kitadani",
      "url":
          "https://github.com/acrosshorizon/palpitate/blob/main/Piano320Kpbs/We%20Are!%20-%20One%20Piece.mp3?raw=true",
      "coverUrl":
          "https://i.pinimg.com/originals/a0/e7/84/a0e7845832279a1315e9d98624bff6de.jpg",
      "info":
          "https://www.youtube.com/watch?v=_iHe7-RhP1I",
      "cover": "(Cover by Animenz Piano Sheets)"
    },
    {
      "title": "Doraemon no Uta (Doraemon OST)",
      "singer": "Shunsuke Kikuchi",
      "url":
          "https://github.com/acrosshorizon/palpitate/blob/main/Piano320Kpbs/Doraemon%20No%20Uta%20_%20Piano%20Cover%20by%20Upwan%20Jindal.mp3?raw=true",
      "coverUrl":
          "https://cdn.substack.com/image/fetch/w_1456,c_limit,f_auto,q_auto:good,fl_lossy/https%3A%2F%2Fbucketeer-e05bbc84-baa3-437e-9518-adb32be77984.s3.amazonaws.com%2Fpublic%2Fimages%2Ff8bbeb18-a27f-46aa-888c-e0b9b9632770_304x300.gif",
      "info":
          "https://www.youtube.com/watch?v=dX9JsEdLWCs",
      "cover": "(Cover by Upwan Jindal)"
    },
    {
      "title": "Blue Bird (Naruto OST)",
      "singer": "Ikimono-gakari",
      "url":
          "https://github.com/acrosshorizon/palpitate/blob/main/Piano320Kpbs/Blue%20Bird%20-%20Naruto%20Shippuuden%20OP3.mp3?raw=true",
      "coverUrl":
          "https://64.media.tumblr.com/fca73ee9e25c63bbce780ddd5d262516/452a373d2bf1613d-47/s500x750/08346212ae4c61d407daf44857c7ea5917a43e58.gifv",
      "info":
          "https://www.youtube.com/watch?v=FTrJ-J_lsr0",
      "cover": "(Cover by Upwan Jindal)"
    },
    {
      "title": "Guren no Yumiya (Attack On Titan OST Season 1)",
      "singer": "Linked Horizon",
      "url":
          "https://github.com/acrosshorizon/palpitate/blob/main/Piano320Kpbs/Attack%20on%20Titan%20-%20Opening%201%20Theme%20_%20Guren%20no%20Yumiya.mp3?raw=true",
      "coverUrl":
          "https://ae01.alicdn.com/kf/HTB1OJA2IVXXXXaRXXXXq6xXFXXX6/Attack-On-Titan-Anime-Characters-45-45CM-Square-Pillow-Case-35692.jpg",
      "info":
          "https://www.youtube.com/watch?v=MIUQGbA8B4k",
      "cover": "(Cover by Patrik Pietschmann)"
    },
    {
      "title": "Attack on Titan (Attack On Titan Main Theme)",
      "singer": "Hiroyuki Sawano",
      "url":
          "https://github.com/acrosshorizon/palpitate/blob/main/Piano320Kpbs/Attack%20on%20Titan%20(Main%20Theme)%20-%20Attack%20on%20Titan.mp3?raw=true",
      "coverUrl":
          "https://animeware.com/wp-content/uploads/2020/11/1932-8c836b.jpeg",
      "info":
          "https://www.youtube.com/watch?v=69lx6TvQTFg",
      "cover": "(Cover by Animenz Piano Sheets)"
    },
    {
      "title": "Doraemon no Uta (Doraemon OST)",
      "singer": "Shunsuke Kikuchi",
      "url":
          "https://github.com/acrosshorizon/palpitate/blob/main/Guitar320Kpbs/Doraemon%20no%20Uta%20-%20Fingerstyle%20Guitar.mp3?raw=true",
      "coverUrl":
          "https://media3.giphy.com/media/TkDVr6D3OgqEqcLIYP/giphy.gif?cid=790b76116949e012a2f26ad973b253543a9dd053346e150a&rid=giphy.gif&ct=s",
      "info":
          "https://www.youtube.com/watch?v=Z26lVIkH4KQ",
      "cover": "(Cover by Jakarudi Main Gitar)"
    },
    {
      "title": "Sparkle (Your Name OST)",
      "singer": "Radwimps",
      "url":
          "https://github.com/acrosshorizon/palpitate/blob/main/Piano320Kpbs/Sparkle%20-%20Ru's%20Piano%20Ru%E5%91%B3%E6%98%A5%E6%8D%B2.mp3?raw=true",
      "coverUrl":
          "https://c.tenor.com/dpeYu-pi2mQAAAAM/your-name-kimi-no-na-wa.gif",
      "info":
          "https://www.youtube.com/watch?v=LO_C_ZAGvoU",
      "cover": "(Cover by Ru's Piano Ru味春捲)"
    },
    {
      "title": "We'll Be Alright - (Weathering With You OST)",
      "singer": "Radwimps",
      "url":
          "https://github.com/acrosshorizon/palpitate/blob/main/Piano320Kpbs/We'll%20Be%20Alright%20-%20Ru's%20Piano%20Ru%E5%91%B3%E6%98%A5%E6%8D%B2.mp3?raw=true",
      "coverUrl":
          "https://i.pinimg.com/564x/52/88/58/528858a87e4928bc04eaf00db1f1abd4.jpg",
      "info":
          "https://www.youtube.com/watch?v=MIFNHiFdqB8",
      "cover": "(Cover by Ru's Piano Ru味春捲)"
    },
    {
      "title": "Sangatsu Kokonoka (9th March)",
      "singer": "Remioromen",
      "url":
          "https://github.com/acrosshorizon/palpitate/blob/main/Piano320Kpbs/Sangatsu%20Kokonoka%20(9%20March).mp3?raw=true",
      "coverUrl":
          "https://i.pinimg.com/564x/42/ec/34/42ec34b74120ef964e8b78101ff59849.jpg",
      "info":
          "https://www.youtube.com/watch?v=qo6p6TX2VkI",
      "cover": "(Cover by Ray Krislianggi - AniMusic)"
    },
    {
      "title": "Always With Me (Spirit Away)",
      "singer": "Youmi Kimura",
      "url":
          "https://github.com/acrosshorizon/palpitate/blob/main/Guitar/(Spirited%20Away)%20Always%20With%20Me%20-%20Sungha%20Jung.mp3?raw=true",
      "coverUrl":
          "https://i1.sndcdn.com/artworks-000154884197-y299a3-t500x500.jpg",
      "info":
          "https://www.youtube.com/watch?v=EIcwEj9uzkk&list=PLTpeyQJ-cKQfkJ12WuqDbbYPYJkdv7Usm&index=115",
      "cover": "(Cover by Sungha Jung)"
    },
    {
      "title": "Best Friend",
      "singer": "Kana Nishino",
      "url":
          "https://github.com/acrosshorizon/palpitate/blob/main/Guitar320Kpbs/Kana%20Nishino%20-%20Best%20Friend%20-%20Fingerstyle%20cover%20-%20(roms%20CHANNEL).mp3?raw=true",
      "coverUrl":
          "https://i.pinimg.com/564x/55/8b/3e/558b3e753742dc9c3746bdb56870175d.jpg",
      "info":
          "https://www.youtube.com/watch?v=OcnxcRJymaQ&list=PLTpeyQJ-cKQfkJ12WuqDbbYPYJkdv7Usm",
      "cover": "(Cover by roms CHANNEL)"
    },
    {
      "title": "Sparkle (Your Name OSt)",
      "singer": "Radwimps",
      "url":
          "https://github.com/acrosshorizon/palpitate/blob/main/Guitar/(Your%20Name)%20Sparkle%20-%20Sungha%20Jung.mp3?raw=true",
      "coverUrl":
          "https://i.pinimg.com/originals/f7/f2/79/f7f279cede0a314f109f5e04c78af05f.gif",
      "info":
          "https://www.youtube.com/watch?v=_u_SrYBSr3c&list=PLTpeyQJ-cKQfkJ12WuqDbbYPYJkdv7Usm&index=109",
      "cover": "(Cover by Sungha Jung)"
    },
    {
      "title": "It Was A Good Day",
      "singer": "Depapepe",
      "url":
          "https://github.com/acrosshorizon/palpitate/blob/main/Guitar/Depapepe%20%E3%81%84%E3%81%84%E6%97%A5%E3%81%A0%E3%81%A3%E3%81%9F%E3%81%AD%20It%20Was%20A%20Good%20Day%20%20Guitar.mp3?raw=true",
      "coverUrl":
          "https://i.pinimg.com/564x/cc/be/c3/ccbec33968405a288041dd3a3621ac66.jpg",
      "info": "https://www.youtube.com/watch?v=VzkZDBEjDR4&list=PLTpeyQJ-cKQfkJ12WuqDbbYPYJkdv7Usm&index=34",
      "cover": "(Cover by Thien An Nguyen)"
    },
    {
      "title": "Is There Still Anything That Love Can Do?",
      "singer": "Radwimps",
      "url":
          "https://github.com/acrosshorizon/palpitate/blob/main/Guitar/Is%20There%20Still%20Anything%20That%20Love%20Can%20Do%20Weathering%20With%20You%20-%20Sungha%20Jung.mp3?raw=true",
      "coverUrl":
          "https://i.pinimg.com/564x/ab/dd/49/abdd497fd21951ea1038e22433fb572f.jpg",
      "info":
          "https://www.youtube.com/watch?v=oTgVtTh-rY4&list=PLTpeyQJ-cKQfkJ12WuqDbbYPYJkdv7Usm&index=61",
      "cover": "(Cover by Sungha Jung)"
    },
    {
      "title": "Nandemonaiya",
      "singer": "Radwimps",
      "url":
          "https://github.com/acrosshorizon/palpitate/blob/main/Guitar/Nandemonaiya%20Guitar%20Cover%20by%20Edward%20Ong.mp3?raw=true",
      "coverUrl":
          "https://i.pinimg.com/736x/1e/6a/e3/1e6ae3dd17cbfd089bd07ee50d4cee18.jpg",
      "info":
          "https://www.youtube.com/watch?v=jI8YraI4CP0&list=PLTpeyQJ-cKQfkJ12WuqDbbYPYJkdv7Usm&index=65",
      "cover": "(Cover by Edward Ong)"
    },
    {
      "title": "Zen Zen Zense (Your Name)",
      "singer": "Radwimps",
      "url":
          "https://github.com/acrosshorizon/palpitate/blob/main/Guitar/Zenzenzense-%20YourNameOST-Guitar.mp3?raw=true",
      "coverUrl":
          "https://i.pinimg.com/564x/83/75/4d/83754d9c24901ad643a403b6846e2e08.jpg",
      "info":
          "https://www.youtube.com/watch?v=CNG8u-uNprM&list=PLTpeyQJ-cKQfkJ12WuqDbbYPYJkdv7Usm&index=7",
      "cover": "(Cover by Edward Ong)"
    },
    {
      "title": "Irony",
      "singer": "Majiko",
      "url":
          "https://github.com/acrosshorizon/palpitate/blob/main/Guitar/Irony%20%E3%82%A2%E3%82%A4%E3%83%AD%E3%83%8B%20Vocaloid%20Fingerstyle%20Guitar%20Cover%20TABS(JayJay%20Fingerstyle).mp3?raw=true",
      "coverUrl":
          "https://i.pinimg.com/474x/8a/ca/92/8aca92fedcdb8f60ed1470894842fd8c.jpg",
      "info":
          "https://www.youtube.com/watch?v=6wuYLzQkzJw&list=PLTpeyQJ-cKQfkJ12WuqDbbYPYJkdv7Usm&index=11",
      "cover": "(Cover by JayJay Fingerstyle)"
    },
    {
      "title": "Renai Circulation",
      "singer": "Kana Hanazawa",
      "url":
          "https://github.com/acrosshorizon/palpitate/blob/main/Guitar/Renai%20Circulation%20on%20Guitar%20ft%20The%20Anime%20Man(Eddie%20van%20der%20Meer).mp3?raw=true",
      "coverUrl":
          "https://i.pinimg.com/564x/17/6f/7a/176f7a1abb4d32850bcab6ee2b3baf27.jpg",
      "info":
          "https://www.youtube.com/watch?v=1MgIqz66NZA&list=PLTpeyQJ-cKQfkJ12WuqDbbYPYJkdv7Usm&index=16",
      "cover": "(Cover by Eddie van der Meer)"
    },
    {
      "title": "Renai Circulation",
      "singer": "Kana Hanazawa",
      "url":
          "https://github.com/acrosshorizon/palpitate/blob/main/Guitar/Renai%20Circulation%E6%81%8B%E6%84%9B%E3%82%B5%E3%83%BC%E3%82%AD%E3%83%A5%E3%83%AC%E3%83%BC%E3%82%B7%E3%83%A7%E3%83%B3fingerstyle%20cover%20%20Kana%20Hanazawa(Iqbal%20Gumilar).mp3?raw=true",
      "coverUrl":
          "https://i.pinimg.com/474x/8c/c0/df/8cc0dfc0a980134f15cb1c4c0f8b552d.jpg",
      "info":
          "https://www.youtube.com/watch?v=uZYCWDtSmQY&list=PLTpeyQJ-cKQfkJ12WuqDbbYPYJkdv7Usm&index=14",
      "cover": "(Cover by Iqbal Gumilar)"
    },
    {
      "title": "Summertime",
      "singer": "Cinnamons & Evening cinema",
      "url":
          "https://github.com/acrosshorizon/palpitate/blob/main/Guitar/summertime%20%20cinnamons%20evening%20cinema%20%20guitar(paul%20iballa).mp3?raw=true",
      "coverUrl":
          "https://m.media-amazon.com/images/I/610jev8sNeL._SS500_.jpg",
      "info":
          "https://www.youtube.com/watch?v=b7hPRyygMeI&list=PLTpeyQJ-cKQfkJ12WuqDbbYPYJkdv7Usm&index=18",
      "cover": "(Cover by Paul Iballa)"
    },
    {
      "title": "Irony",
      "singer": "Majiko",
      "url":
          "https://github.com/acrosshorizon/palpitate/blob/main/Guitar/Irony%20%E3%82%A2%E3%82%A4%E3%83%AD%E3%83%8B%20Vocaloid%20Fingerstyle%20Guitar%20Cover%20TABS(JayJay%20Fingerstyle).mp3?raw=true",
      "coverUrl":
          "https://i.pinimg.com/564x/79/35/d5/7935d5bb073005aa00dff9d3ed5d2aa0.jpg",
      "info":
          "https://www.youtube.com/watch?v=l_9TGpuIAvk&list=PLTpeyQJ-cKQfkJ12WuqDbbYPYJkdv7Usm&index=7",
      "cover": "(Cover by Natanael A.)"
    },
    {
      "title": "Chiisana Koi no Uta",
      "singer": "Mongol800",
      "url":
          "https://github.com/acrosshorizon/palpitate/blob/main/Guitar320Kpbs/Chiisana%20Koi%20no%20Uta%20%20Fingerstyle%20Guitar%20(Leon%20Alex).mp3?raw=true",
      "coverUrl":
          "https://i.pinimg.com/564x/9c/97/49/9c97490921e8ff904adeec0183ebee29.jpg",
      "info":
          "https://www.youtube.com/watch?v=iGDv17HKPuM&list=PLTpeyQJ-cKQfkJ12WuqDbbYPYJkdv7Usm&index=36",
      "cover": "(Cover by Leon Alex)"
    },
    {
      "title": "Uchiage Hanabi",
      "singer": "Daoko and Kenshi Yonezu",
      "url":
          "https://github.com/acrosshorizon/palpitate/blob/main/MusicBox/Uchiage%20Hanabi%20Music%20Box%20Cover.mp3?raw=true",
      "coverUrl":
          "https://i.pinimg.com/564x/16/b7/11/16b711608d72dd16e1662944726ea428.jpg",
      "info":
          "https://www.youtube.com/watch?v=S8vyJMsXTXA&list=PLTpeyQJ-cKQfkJ12WuqDbbYPYJkdv7Usm&index=1",
      "cover": "(Cover by Flow Music)"
    },
    {
      "title": "GUMI",
      "singer": "Hoshi Ai",
      "url":
          "https://github.com/acrosshorizon/palpitate/blob/main/MusicBox/GUMI%20-%20Hoshi%20Ai%20Music%20Box.mp3?raw=true",
      "coverUrl":
          "https://i.pinimg.com/564x/4b/00/65/4b0065c9fd27d0ee873069776a8f079c.jpg",
      "info":
          "https://www.youtube.com/watch?v=t-DEjAzPzeA&list=PLTpeyQJ-cKQfkJ12WuqDbbYPYJkdv7Usm&index=2",
      "cover": "(Cover by Flow Music)"
    },
    {
      "title": "Lemon",
      "singer": "Kenshi Yonezu",
      "url":
          "https://github.com/acrosshorizon/palpitate/blob/main/MusicBox/Lemon%20-%20Kenshi%20Yonezu%20Music%20Box%20Cover.mp3?raw=true",
      "coverUrl":
          "https://i.pinimg.com/564x/15/93/ed/1593ed12f2315a66b9552da96c5d3cda.jpg",
      "info":
          "https://www.youtube.com/watch?v=LdYB-YoAOjc&list=PLTpeyQJ-cKQfkJ12WuqDbbYPYJkdv7Usm&index=4",
      "cover": "(Cover by Flow Music)"
    },
    {
      "title": "March 9 (1リットルの涙)",
      "singer": "Remioromen",
      "url":
          "https://github.com/acrosshorizon/palpitate/blob/main/MusicBox/3%E6%9C%889%E6%97%A5%E3%83%AC%E3%83%9F%E3%82%AA%E3%83%AD%E3%83%A1%E3%83%B3(MusicBox).mp3?raw=true",
      "coverUrl":
          "https://i.pinimg.com/564x/59/ad/c4/59adc41d3df46ba6534ade35b5133335.jpg",
      "info":
          "https://www.youtube.com/watch?v=2rlEyqfJJHc&list=PLTpeyQJ-cKQfkJ12WuqDbbYPYJkdv7Usm&index=28",
      "cover": "(Cover by R3 Music Box )"
    },
    {
      "title": "Konayuki(1リットルの涙)",
      "singer": "Remioromen",
      "url":
          "https://github.com/acrosshorizon/palpitate/blob/main/MusicBox/Konayuki.mp3?raw=true",
      "coverUrl":
          "https://pbs.twimg.com/media/ErPn_iJW4AMcpAp.jpg",
      "info":
          "https://www.youtube.com/watch?v=3PS_lShi7nQ&list=PLTpeyQJ-cKQfkJ12WuqDbbYPYJkdv7Usm&index=25",
      "cover": "(Cover by Relax α Wave - Topic)"
    },
    {
      "title": "Grand Escape (Weathering with You OST)",
      "singer": "Radwimps",
      "url":
          "https://github.com/acrosshorizon/palpitate/blob/main/MusicBox/Weathering%20With%20You%20OST%20-%20Grand%20Escape%20(MusicBox).mp3?raw=true",
      "coverUrl":
          "https://avatarfiles.alphacoders.com/200/200974.jpg",
      "info":
          "https://www.youtube.com/watch?v=Wk5uoaQTzc0&list=PLTpeyQJ-cKQfkJ12WuqDbbYPYJkdv7Usm&index=95",
      "cover": "(Cover by Musicbox cover)"
    },
    {
      "title": "Carrying You (Castle in the Sky OST)",
      "singer": "Azumi Inoue",
      "url":
          "https://github.com/acrosshorizon/palpitate/blob/main/MusicBox/%E5%90%9B%E3%82%92%E3%81%AE%E3%81%9B%E3%81%A6%E4%BA%95%E4%B8%8A%E3%81%82%E3%81%9A%E3%81%BF(MusicBox).mp3?raw=true",
      "coverUrl":
          "https://i1.sndcdn.com/artworks-000085328517-s0prur-t500x500.jpg",
      "info":
          "https://www.youtube.com/watch?v=OaQhzOaB2xo&list=PLTpeyQJ-cKQfkJ12WuqDbbYPYJkdv7Usm&index=29",
      "cover": "(Cover by R3 Music Box)"
    },
    {
      "title": "Summertime",
      "singer": "Cinnamons & Evening Cinema",
      "url":
          "https://github.com/acrosshorizon/palpitate/blob/main/MusicBox/Summertime%20Cinnamons%20x%20Evening%20Cinema%20Music%20Box%20Cover(Violin%20X%20Cello%20Official).mp3?raw=true",
      "coverUrl":
          "https://i.pinimg.com/564x/11/87/23/1187235ddef1caa590283cdc72466ac9.jpg",
      "info":
          "https://www.youtube.com/watch?v=8d78vtaZVn8&list=PLTpeyQJ-cKQfkJ12WuqDbbYPYJkdv7Usm&index=19",
      "cover": "(Cover by Violin X Cello Official)"
    },
    {
      "title": "Always With Me",
      "singer": "Youmi Kimura",
      "url":
          "https://github.com/acrosshorizon/palpitate/blob/main/Piano/Alwayswithme-SpiritedAwayOST.mp3?raw=true",
      "coverUrl":
          "https://i.pinimg.com/564x/57/b7/95/57b79500c34f0229f0bc882e6507cc20.jpg",
      "info":
          "https://www.youtube.com/watch?v=oK3J0xI_KaY&list=PLTpeyQJ-cKQfkJ12WuqDbbYPYJkdv7Usm&index=5",
      "cover": "(Cover by ToWiMe)"
    },
    {
      "title": "Lemon",
      "singer": "Kenshi Yonezu",
      "url":
          "https://github.com/acrosshorizon/palpitate/blob/main/Piano/Lemon%20-%20Yonezu%20Kenshi%20l%204hands%20piano.mp3?raw=true",
      "coverUrl":
          "https://i.pinimg.com/564x/59/1e/f1/591ef1b1fbd29ae93d3647e6b21f377e.jpg",
      "info":
          "https://www.youtube.com/watch?v=07iRsCH1aRo&list=PLTpeyQJ-cKQfkJ12WuqDbbYPYJkdv7Usm&index=40",
      "cover": "(Cover by BELLA&LUCAS 벨라앤루카스)"
    },
    {
      "title": "Sangatsu Kokonoka (March 9)",
      "singer": "Remioromen (1リットルの涙)",
      "url":
          "https://github.com/acrosshorizon/palpitate/blob/main/Piano/Sangatsu%20Kokonoka-%20Remioromen(Piano%20March%209).mp3?raw=true",
      "coverUrl":
          "https://logo-imagecluster.img.mixi.jp/photo/comm/2/86/440286_122.jpg",
      "info":
          "https://www.youtube.com/watch?v=5SUsd0zIo9k&list=PLTpeyQJ-cKQfkJ12WuqDbbYPYJkdv7Usm&index=27",
      "cover": "(Cover by Ray Krislianggi - AniMusic)"
    },
    {
      "title": "Sparkle (Your Name)",
      "singer": "Radwimps",
      "url":
          "https://github.com/acrosshorizon/palpitate/blob/main/Piano/Sparkle%20-%20Kimi%20no%20Nawa%20(%E5%90%9B%E3%81%AE%E5%90%8D%E3%81%AF)%20OST%20l%204hands%20piano.mp3?raw=true",
      "coverUrl":
          "https://i.pinimg.com/564x/ae/15/f4/ae15f4431e360a5997dfa86ecc3e11ee.jpg",
      "info":
          "https://www.youtube.com/watch?v=Gbb3fu631pc&list=PLTpeyQJ-cKQfkJ12WuqDbbYPYJkdv7Usm&index=38",
      "cover": "(Cover by BELLA&LUCAS 벨라앤루카스)"
    },
    {
      "title": "Zen Zen Zense (Your Name)",
      "singer": "Radwimps",
      "url":
          "https://github.com/acrosshorizon/palpitate/blob/main/Piano/Zen%20Zen%20Zense%20Kimi%20no%20Nawa%204hands%20piano.mp3?raw=true",
      "coverUrl":
          "https://i.pinimg.com/564x/83/75/4d/83754d9c24901ad643a403b6846e2e08.jpg",
      "info":
          "https://www.youtube.com/watch?v=1g0xorm_sJw&list=PLTpeyQJ-cKQfkJ12WuqDbbYPYJkdv7Usm&index=39",
      "cover": "(Cover by BELLA&LUCAS 벨라앤루카스)"
    },
    {
      "title": "Irony",
      "singer": "Majiko",
      "url":
          "https://github.com/acrosshorizon/palpitate/blob/main/Piano/Hatsune%20Miku%20Irony%20%E3%82%A2%E3%82%A4%E3%83%AD%E3%83%8B%20piano%20cover(Xxoo00O00ooxX).mp3?raw=true",
      "coverUrl":
          "https://i.pinimg.com/736x/af/7c/68/af7c68795fa9a000dd3c6ce3a1f7cd61.jpg",
      "info":
          "https://www.youtube.com/watch?v=rZ5NFnG5h_k&list=PLTpeyQJ-cKQfkJ12WuqDbbYPYJkdv7Usm&index=11",
      "cover": "(Cover by Xxoo00O00ooxX)"
    },
    {
      "title": "Renai Circulation",
      "singer": "Kana Hanazawa",
      "url":
          "https://github.com/acrosshorizon/palpitate/blob/main/Piano/Renai%20Circulation%20%20Kana%20Hanazawa%20%20Bakemonogatari%20OP%204%20Piano(Fonzi%20M%20-%20Melodies%20on%20Piano).mp3?raw=true",
      "coverUrl":
          "https://i.pinimg.com/474x/60/a9/43/60a94300890d84fefecce018983a2db7.jpg",
      "info":
          "https://www.youtube.com/watch?v=zZYx2C4oY70&list=PLTpeyQJ-cKQfkJ12WuqDbbYPYJkdv7Usm&index=16",
      "cover": "(Cover by Fonzi M - Melodies on Piano)"
    },
    {
      "title": "Renai Circulation",
      "singer": "Kana Hanazawa",
      "url":
          "https://github.com/acrosshorizon/palpitate/blob/main/Piano/Renai%20Circulation%20%E3%83%94%E3%82%A2%E3%83%8E(Pan%20Piano).mp3?raw=true",
      "coverUrl":
          "https://i1.sndcdn.com/artworks-000460685424-c47haz-t500x500.jpg",
      "info":
          "https://www.youtube.com/watch?v=GNBwkNo893k&list=PLTpeyQJ-cKQfkJ12WuqDbbYPYJkdv7Usm&index=14",
      "cover": "(Cover by Pan Piano)"
    },
    {
      "title": "Harehare Ya",
      "singer": "Maigo Hanyuu",
      "url":
          "https://github.com/acrosshorizon/palpitate/blob/main/Piano320Kpbs/Harehare%20Ya%20Sheet%20music%20Piano%20(Annan).mp3?raw=true",
      "coverUrl":
          "https://i1.sndcdn.com/artworks-DVKaOuDNHuaEULue-i2TcWw-t500x500.jpg",
      "info":
          "https://www.youtube.com/watch?v=k5RLIsMOsLg&list=PLTpeyQJ-cKQfkJ12WuqDbbYPYJkdv7Usm&index=39",
      "cover": "(Cover by Annan)"
    },
    {
      "title": "Kokoronashi Somehow",
      "singer": "Sou",
      "url":
          "https://github.com/acrosshorizon/palpitate/blob/main/Piano320Kpbs/Kokoronashi%20Somehow%20%E5%BF%83%E5%81%9A%E3%81%97%20piano(dinhosaurrx~).mp3?raw=true",
      "coverUrl":
          "https://i.scdn.co/image/ab67616d0000b273f672cfe50a513713ea7cdc85",
      "info":
          "https://www.youtube.com/watch?v=_fGm_teekjo&list=PLTpeyQJ-cKQfkJ12WuqDbbYPYJkdv7Usm&index=37",
      "cover": "(Cover by dinhosaurrx~)"
    },
    {
      "title": "Kokoronashi",
      "singer": "Sou",
      "url":
          "https://github.com/acrosshorizon/palpitate/blob/main/Piano320Kpbs/Kokoronashi%E8%9D%B6Piano%20Cover(SLSMusic).mp3?raw=true",
      "coverUrl":
          "https://i1.sndcdn.com/artworks-000129070881-33exfz-t500x500.jpg",
      "info":
          "https://www.youtube.com/watch?v=H3REpwirkzc&list=PLTpeyQJ-cKQfkJ12WuqDbbYPYJkdv7Usm&index=36",
      "cover": "(Cover by SLSMusic)"
    },
    {
      "title": "Sparkle (Your Name)",
      "singer": "Radwimps",
      "url":
          "https://github.com/acrosshorizon/palpitate/blob/main/Piano320Kpbs/Sparkle%20%20RADWIMPS(Animenz%20Piano%20Sheets).mp3?raw=true",
      "coverUrl":
          "https://i.pinimg.com/564x/33/17/e4/3317e4e44f971d961cd93a411fa03837.jpg",
      "info":
          "https://www.youtube.com/watch?v=cKgnDmpb4BU&list=PLTpeyQJ-cKQfkJ12WuqDbbYPYJkdv7Usm&index=44",
      "cover": "(Cover by Animenz Piano Sheets)"
    },
    {
      "title": "Is There Still Anything That Love Can Do? (Weathering With You)",
      "singer": "Radwimps",
      "url":
          "https://github.com/acrosshorizon/palpitate/blob/main/Piano320Kpbs/There%20Still%20Anything%20That%20Love%20Can%20Do(Ru's%20Piano%20Ru%E5%91%B3%E6%98%A5%E6%8D%B2).mp3?raw=true",
      "coverUrl":
          "https://i.pinimg.com/originals/6d/4c/ec/6d4cec0de1ca4f57e78f2a99c09474cb.gif",
      "info":
          "https://www.youtube.com/watch?v=RWAj-fX5CyE&list=PLTpeyQJ-cKQfkJ12WuqDbbYPYJkdv7Usm&index=6",
      "cover": "(Cover by Ru's Piano Ru味春捲)"
    },
    {
      "title": "PLANET",
      "singer": "ラムジ",
      "url":
          "https://github.com/acrosshorizon/palpitate/blob/main/Ukulele/PLANET%E3%83%A9%E3%83%A0%E3%82%B8%20Fingerstyle%20Ukulele%20Cover(EnyaMusic%20Anny).mp3?raw=true",
      "coverUrl":
          "https://i.pinimg.com/originals/24/13/13/241313ad5124729a15476cdced40ba9f.gif",
      "info":
          "https://www.youtube.com/watch?v=JuBxQes1rtk&list=PLTpeyQJ-cKQfkJ12WuqDbbYPYJkdv7Usm&index=21",
      "cover": "(Cover by EnyaMusic Anny)"
    },
    {
      "title": "Watashi no Uso",
      "singer": "Your Lie in April OST",
      "url":
          "https://github.com/acrosshorizon/palpitate/blob/main/Violin/your%20lie%20in%20aprilwatashi%20no%20uso%20LilyPichu.mp3?raw=true",
      "coverUrl":
          "https://i1.wp.com/66.media.tumblr.com/346e7c2dc66daff8e45c0ce881889033/tumblr_nq9xw2wKVE1s5f9ado1_500.gif",
      "info":
          "https://www.youtube.com/watch?v=iW_P2UPkpc4&list=PLTpeyQJ-cKQfkJ12WuqDbbYPYJkdv7Usm&index=11",
      "cover": "(Cover by LilyPichu)"
    },
    {
      "title": "「名探偵コナン」メインテーマ (Detective Conan OST)",
      "singer": "Katsuo Ohno",
      "url":
          "https://github.com/acrosshorizon/palpitate/blob/main/Piano320Kpbs/Detective%20Conan%20OST%20(%E6%9C%88%E9%87%8E%E3%82%A2%E3%82%A4%E3%83%A9%E3%80%88Aira%20Piano%E3%80%89).mp3?raw=true",
      "coverUrl":
          "https://data.whicdn.com/images/156253303/original.gif",
      "info":
          "https://www.youtube.com/watch?v=3B19vmd_-Y4&list=PLTpeyQJ-cKQfkJ12WuqDbbYPYJkdv7Usm&index=17",
      "cover": "(Cover by 月野アイラ〈Aira Piano〉)"
    }
  ]
}
